benchmarks/__init__.py
benchmarks/benchmark_attr_equiv_blocker.py
benchmarks/benchmark_blackbox_blocker.py
benchmarks/benchmark_debugblocker.py
benchmarks/benchmark_down_sample_sampler.py
benchmarks/benchmark_overlap_blocker.py
benchmarks/benchmark_rule_based_blocker.py
benchmarks/benchmark_sn_blocker.py
py_entitymatching/__init__.py
py_entitymatching/blocker/__init__.py
py_entitymatching/blocker/attr_equiv_blocker.py
py_entitymatching/blocker/black_box_blocker.py
py_entitymatching/blocker/blocker.py
py_entitymatching/blocker/overlap_blocker.py
py_entitymatching/blocker/rule_based_blocker.py
py_entitymatching/blocker/sn_blocker.py
py_entitymatching/blockercombiner/__init__.py
py_entitymatching/blockercombiner/blockercombiner.py
py_entitymatching/catalog/__init__.py
py_entitymatching/catalog/catalog.py
py_entitymatching/catalog/catalog_manager.py
py_entitymatching/dask/__init__.py
py_entitymatching/dask/dask_attr_equiv_blocker.py
py_entitymatching/dask/dask_black_box_blocker.py
py_entitymatching/dask/dask_down_sample.py
py_entitymatching/dask/dask_dtmatcher.py
py_entitymatching/dask/dask_extract_features.py
py_entitymatching/dask/dask_logregmatcher.py
py_entitymatching/dask/dask_nbmatcher.py
py_entitymatching/dask/dask_overlap_blocker.py
py_entitymatching/dask/dask_rfmatcher.py
py_entitymatching/dask/dask_rule_based_blocker.py
py_entitymatching/dask/dask_svm_matcher.py
py_entitymatching/dask/dask_xgboost_matcher.py
py_entitymatching/dask/daskmlmatcher.py
py_entitymatching/dask/utils.py
py_entitymatching/datasets/ACM.csv
py_entitymatching/datasets/DBLP.csv
py_entitymatching/datasets/acm_demo.csv
py_entitymatching/datasets/acm_demo.metadata
py_entitymatching/datasets/dblp_acm_demo_labels.csv
py_entitymatching/datasets/dblp_demo.csv
py_entitymatching/datasets/final_matches.csv
py_entitymatching/datasets/labeled_data_demo.csv
py_entitymatching/datasets/person_table_A.csv
py_entitymatching/datasets/person_table_A.metadata
py_entitymatching/datasets/person_table_B.csv
py_entitymatching-0.4.0.dist-info/LICENSE
py_entitymatching-0.4.0.dist-info/METADATA
py_entitymatching-0.4.0.dist-info/WHEEL
py_entitymatching-0.4.0.dist-info/top_level.txt
py_entitymatching-0.4.0.dist-info/RECORD
